balint1/__init__.py
balint1/balint1.py
balint1-0.1.0.dist-info/METADATA
balint1-0.1.0.dist-info/WHEEL
balint1-0.1.0.dist-info/top_level.txt
balint1-0.1.0.dist-info/RECORD
